mulp/MultiLayerRanker.py
mulp/__init__.py
mulp-1.1.1.dist-info/LICENSE
mulp-1.1.1.dist-info/METADATA
mulp-1.1.1.dist-info/WHEEL
mulp-1.1.1.dist-info/top_level.txt
mulp-1.1.1.dist-info/RECORD
