Metadata-Version: 2.1
Name: mulp
Version: 1.1.1
Summary: Python implementation of the Multilayer Credit Scoring algorithm from Óskarsdóttir & Bravo (2019)
Author: Cristián Bravo, Sigurjon Thorsteinsson, Emiliano Penaloza, María Óskarsdóttir
Author-email: cbravoro@uwo.ca
Project-URL: GitHub, https://github.com/Banking-Analytics-Lab/mulp
Project-URL: Changelog, https://github.com/Banking-Analytics-Lab/mulp/blob/master/CHANGELOG.md
Classifier: Programming Language :: Python :: 3.11
Classifier: License :: OSI Approved :: GNU General Public License v3 (GPLv3)
Classifier: Operating System :: OS Independent
Requires-Python: >=3.11
License-File: LICENSE
Requires-Dist: numpy >=2.0.2
Requires-Dist: networkx >=3.4.2
Requires-Dist: scipy >=1.14.1
Requires-Dist: scikit-learn >=1.5.2
Requires-Dist: pandas >=2.2.3
Requires-Dist: igraph >=0.11.2
